redun_psij/__init__.py
redun_psij/_singleton.py
redun_psij/executor.py
redun_psij/job_attributes.py
redun_psij-0.1.1.dist-info/licenses/LICENSE
redun_psij-0.1.1.dist-info/WHEEL
redun_psij-0.1.1.dist-info/METADATA
redun_psij-0.1.1.dist-info/RECORD
