Metadata-Version: 2.4
Name: redun_psij
Version: 0.1.1
Summary: PSI/J Executor for Redun
Author-email: Simon Guest <simon.guest@agresearch.co.nz>
Requires-Python: >=3.10
License-Expression: Apache-2.0
Classifier: Programming Language :: Python :: 3
Classifier: Operating System :: OS Independent
License-File: LICENSE
Requires-Dist: redun
Requires-Dist: psij-python
Requires-Dist: jsonnet
Requires-Dist: sphinx ; extra == "docs"
Requires-Dist: sphinx-autobuild ; extra == "docs"
Requires-Dist: sphinx-rtd-theme ; extra == "docs"
Provides-Extra: docs
